odoo/addons/mrp_bom_matrix_report/README.rst
odoo/addons/mrp_bom_matrix_report/__init__.py
odoo/addons/mrp_bom_matrix_report/__manifest__.py
odoo/addons/mrp_bom_matrix_report/models/__init__.py
odoo/addons/mrp_bom_matrix_report/models/mrp_bom_matrix_report.py
odoo/addons/mrp_bom_matrix_report/security/ir.model.access.csv
odoo/addons/mrp_bom_matrix_report/views/mrp_bom_matrix_report_views.xml
odoo11_addon_mrp_bom_matrix_report-11.0.1.0.0.dist-info/DESCRIPTION.rst
odoo11_addon_mrp_bom_matrix_report-11.0.1.0.0.dist-info/METADATA
odoo11_addon_mrp_bom_matrix_report-11.0.1.0.0.dist-info/RECORD
odoo11_addon_mrp_bom_matrix_report-11.0.1.0.0.dist-info/WHEEL
odoo11_addon_mrp_bom_matrix_report-11.0.1.0.0.dist-info/metadata.json
odoo11_addon_mrp_bom_matrix_report-11.0.1.0.0.dist-info/top_level.txt
